odoo10_addon_web_widget_slickroom-10.0.1.0.0-py2.7-nspkg.pth
odoo/addons/web_widget_slickroom/README.rst
odoo/addons/web_widget_slickroom/__init__.py
odoo/addons/web_widget_slickroom/__manifest__.py
odoo/addons/web_widget_slickroom/static/description/icon.png
odoo/addons/web_widget_slickroom/static/src/js/web_widget_slickroom.js
odoo/addons/web_widget_slickroom/static/src/less/web_widget_slickroom.less
odoo/addons/web_widget_slickroom/static/tests/js/web_widget_slickroom.js
odoo/addons/web_widget_slickroom/templates/assets.xml
odoo/addons/web_widget_slickroom/tests/__init__.py
odoo/addons/web_widget_slickroom/tests/test_ui.py
odoo10_addon_web_widget_slickroom-10.0.1.0.0.dist-info/DESCRIPTION.rst
odoo10_addon_web_widget_slickroom-10.0.1.0.0.dist-info/METADATA
odoo10_addon_web_widget_slickroom-10.0.1.0.0.dist-info/RECORD
odoo10_addon_web_widget_slickroom-10.0.1.0.0.dist-info/WHEEL
odoo10_addon_web_widget_slickroom-10.0.1.0.0.dist-info/metadata.json
odoo10_addon_web_widget_slickroom-10.0.1.0.0.dist-info/namespace_packages.txt
odoo10_addon_web_widget_slickroom-10.0.1.0.0.dist-info/top_level.txt
